LICENSE
setup.cfg
setup.py
shep/__init__.py
shep/error.py
shep/persist.py
shep/state.py
shep/verify.py
shep.egg-info/PKG-INFO
shep.egg-info/SOURCES.txt
shep.egg-info/dependency_links.txt
shep.egg-info/requires.txt
shep.egg-info/top_level.txt
shep/store/base.py
shep/store/file.py
shep/store/noop.py
shep/store/redis.py
shep/store/rocksdb.py
tests/test_file.py
tests/test_item.py
tests/test_noop.py
tests/test_redis.py
tests/test_report.py
tests/test_rocksdb.py
tests/test_state.py
tests/test_store.py
tests/test_verify.py