Metadata-Version: 2.1
Name: shep
Version: 0.3.6
Summary: Multi-state key stores using bit masks
Home-page: https://git.defalsify.org/python-shep
Author: Louis Holbrook
Author-email: dev@holbrook.no
License: GPL3
Keywords: dict,queue
Classifier: Programming Language :: Python :: 3
Classifier: Operating System :: OS Independent
Classifier: Development Status :: 4 - Beta
Classifier: Topic :: Software Development :: Libraries
Classifier: Intended Audience :: Developers
Classifier: License :: OSI Approved :: GNU General Public License v3 or later (GPLv3+)
Requires-Python: >=3.7
Provides-Extra: redis
Provides-Extra: rocksdb
License-File: LICENSE
